{
  "_format": "hh-sol-cache-2",
  "files": {
    "/Users/fangrui/EECE571G/VoteSystem-1/contracts/VoteSystem.sol": {
      "lastModificationDate": 1712336590740,
      "contentHash": "3d7d4d5f9b0feda565f1976627b89998",
      "sourceName": "contracts/VoteSystem.sol",
      "solcConfig": {
        "version": "0.8.24",
        "settings": {
          "evmVersion": "paris",
          "optimizer": {
            "enabled": false,
            "runs": 200
          },
          "outputSelection": {
            "*": {
              "*": [
                "abi",
                "evm.bytecode",
                "evm.deployedBytecode",
                "evm.methodIdentifiers",
                "metadata"
              ],
              "": [
                "ast"
              ]
            }
          }
        }
      },
      "imports": [
        "hardhat/console.sol"
      ],
      "versionPragmas": [
        "^0.8.9"
      ],
      "artifacts": [
        "VoteSystem"
      ]
    },
    "/Users/fangrui/EECE571G/VoteSystem-1/node_modules/hardhat/console.sol": {
      "lastModificationDate": 1712336591877,
      "contentHash": "896f68942c3a20e9ae3c3c5bfd3add54",
      "sourceName": "hardhat/console.sol",
      "solcConfig": {
        "version": "0.8.24",
        "settings": {
          "evmVersion": "paris",
          "optimizer": {
            "enabled": false,
            "runs": 200
          },
          "outputSelection": {
            "*": {
              "*": [
                "abi",
                "evm.bytecode",
                "evm.deployedBytecode",
                "evm.methodIdentifiers",
                "metadata"
              ],
              "": [
                "ast"
              ]
            }
          }
        }
      },
      "imports": [],
      "versionPragmas": [
        ">=0.4.22 <0.9.0"
      ],
      "artifacts": [
        "console"
      ]
    }
  }
}
